{"chunk_definitions":[{"row":9,"row_count":1,"visible":true,"expansion_state":0,"options":{"engine":"r","label":"nice-fig","fig.cap":"Here is a nice figure!","out.width":"80%","fig.asp":0.75,"fig.align":"center"},"document_id":"F12BB44C","chunk_id":"capbfjs1ulc98","chunk_label":"nice-fig"},{"row":18,"row_count":1,"visible":true,"expansion_state":0,"options":{"engine":"r","label":"nice-tab","tidy":false},"document_id":"F12BB44C","chunk_id":"cng0b53ye7gxx","chunk_label":"nice-tab"}],"doc_write_time":1625722166,"chunk_rendered_width":576}